codeagents/__init__.py
codeagents/core.py
codeagents-1.0.0.dist-info/METADATA
codeagents-1.0.0.dist-info/WHEEL
codeagents-1.0.0.dist-info/top_level.txt
codeagents-1.0.0.dist-info/RECORD
